akimbo_ip-0.3.0.dist-info/METADATA
akimbo_ip-0.3.0.dist-info/WHEEL
akimbo_ip-0.3.0.dist-info/license_files/LICENSE
akimbo_ip/utils.py
akimbo_ip/__init__.py
akimbo_ip/accessor.py
akimbo_ip/akimbo_ip.cpython-310-x86_64-linux-gnu.so
akimbo_ip-0.3.0.dist-info/RECORD
