Metadata-Version: 2.1
Name: akimbo-ip
Version: 0.3.0
Classifier: Programming Language :: Rust
Classifier: Programming Language :: Python :: Implementation :: CPython
Classifier: Programming Language :: Python :: Implementation :: PyPy
Requires-Dist: akimbo
License-File: LICENSE
Summary: IP-specific methods for akimbo
Requires-Python: >=3.10
